nbsapi_verify/__init__.py
nbsapi_verify/cli.py
nbsapi_verify/formatting.py
nbsapi_verify/templates/report.html
nbsapi_verify/tests/test_add_solution_to_existing_project_v2_api_projects__project_id__solutions__solution_id__post.tavern.yaml
nbsapi_verify/tests/test_create_new_measure_type_v2_measure_types__post.tavern.yaml
nbsapi_verify/tests/test_create_new_project_v2_api_projects_post.tavern.yaml
nbsapi_verify/tests/test_create_solution_impact_v2_api_impacts_solutions__solution_id__impacts_post.tavern.yaml
nbsapi_verify/tests/test_export_project_deltares_v2_api_projects__project_id__export_deltares_get.tavern.yaml
nbsapi_verify/tests/test_export_project_v2_api_projects__project_id__export_get.tavern.yaml
nbsapi_verify/tests/test_get_api_version_info_api_version_get.tavern.yaml
nbsapi_verify/tests/test_get_contact_contact_get.tavern.yaml
nbsapi_verify/tests/test_get_current_api_version_currentversion_get.tavern.yaml
nbsapi_verify/tests/test_get_solutions_v2_api_solutions_solutions_post.tavern.yaml
nbsapi_verify/tests/test_import_project_v2_api_projects_import_post.tavern.yaml
nbsapi_verify/tests/test_login_for_access_token_auth_token_post.tavern.yaml
nbsapi_verify/tests/test_read_impact_intensities_v2_api_impacts_intensities_get.tavern.yaml
nbsapi_verify/tests/test_read_impact_units_v2_api_impacts_units_get.tavern.yaml
nbsapi_verify/tests/test_read_impact_v2_api_impacts_impacts__impact_id__get.tavern.yaml
nbsapi_verify/tests/test_read_measure_type_v2_measure_types__measure_id__get.tavern.yaml
nbsapi_verify/tests/test_read_measure_types_v2_measure_types__get.tavern.yaml
nbsapi_verify/tests/test_read_nature_based_solution_as_geojson_v2_api_solutions_solutions__solution_id__geojson_get.tavern.yaml
nbsapi_verify/tests/test_read_nature_based_solution_v2_api_solutions_solutions__solution_id__get.tavern.yaml
nbsapi_verify/tests/test_read_project_v2_api_projects__project_id__get.tavern.yaml
nbsapi_verify/tests/test_read_projects_v2_api_projects_get.tavern.yaml
nbsapi_verify-0.2.0.dist-info/METADATA
nbsapi_verify-0.2.0.dist-info/WHEEL
nbsapi_verify-0.2.0.dist-info/entry_points.txt
nbsapi_verify-0.2.0.dist-info/licenses/LICENSE.md
nbsapi_verify-0.2.0.dist-info/RECORD
