Metadata-Version: 2.4
Name: nbsapi_verify
Version: 0.2.0
Summary: Verify an nbsinfra API implementation
Project-URL: Homepage, https://nbsapi.org
Project-URL: Repository, https://github.com/nbsapi/nbsapi_verify
Project-URL: Tracker, https://github.com/nbsapi/nbsapi_verify/issues
Author-email: Stephan Hügel <urschrei@gmail.com>
Maintainer-email: Hrishi Ballal <hrishi@geodesignhub.com>
License: MIT License
License-File: LICENSE.md
Keywords: nbsapi,nbsinfra
Requires-Python: >=3.9
Requires-Dist: click>=8.1.8
Requires-Dist: jinja2>=3.0.0
Requires-Dist: tavern>=2.11.0
Provides-Extra: test
Requires-Dist: pytest>=7.0; extra == 'test'
